hickleable/__init__.py
hickleable-0.2.4.dist-info/LICENSE
hickleable-0.2.4.dist-info/METADATA
hickleable-0.2.4.dist-info/WHEEL
hickleable-0.2.4.dist-info/top_level.txt
hickleable-0.2.4.dist-info/RECORD
