Metadata-Version: 2.1
Name: hickleable
Version: 0.2.4
Summary: A simple decorator to make your classes hickle-able
Home-page: https://github.com/steven-murray/hickleable
Author: Steven Murray
License: mit
Platform: any
Classifier: Development Status :: 5 - Production/Stable
Classifier: Programming Language :: Python
License-File: LICENSE
Requires-Dist: attrs
Requires-Dist: hickle
Provides-Extra: dev
Requires-Dist: hickleable[docs,test] ; extra == 'dev'
Requires-Dist: commitizen ; extra == 'dev'
Provides-Extra: docs
Requires-Dist: sphinx >=1.3 ; extra == 'docs'
Requires-Dist: furo ; extra == 'docs'
Requires-Dist: numpydoc ; extra == 'docs'
Requires-Dist: nbsphinx ; extra == 'docs'
Requires-Dist: ipython ; extra == 'docs'
Provides-Extra: test
Requires-Dist: pre-commit ; extra == 'test'
Requires-Dist: pytest ; extra == 'test'
Requires-Dist: pytest-cov ; extra == 'test'
